apartheid.py
apartheid-0.2.0.dist-info/LICENSE
apartheid-0.2.0.dist-info/WHEEL
apartheid-0.2.0.dist-info/METADATA
apartheid-0.2.0.dist-info/RECORD
